[
  {
    "streamable": "0",
    "image": [
      {
        "size": "small",
        "#text": "https://lastfm.freetls.fastly.net/i/u/34s/2a96cbd8b46e442fc41c2b86b821562f.png"
      },
      {
        "size": "medium",
        "#text": "https://lastfm.freetls.fastly.net/i/u/64s/2a96cbd8b46e442fc41c2b86b821562f.png"
      },
      {
        "size": "large",
        "#text": "https://lastfm.freetls.fastly.net/i/u/174s/2a96cbd8b46e442fc41c2b86b821562f.png"
      },
      {
        "size": "extralarge",
        "#text": "https://lastfm.freetls.fastly.net/i/u/300x300/2a96cbd8b46e442fc41c2b86b821562f.png"
      },
      {
        "size": "mega",
        "#text": "https://lastfm.freetls.fastly.net/i/u/300x300/2a96cbd8b46e442fc41c2b86b821562f.png"
      }
    ],
    "mbid": "21f8e84f-f6ce-4fb4-b79f-9c4c24774f64",
    "url": "https://www.last.fm/music/Palmy",
    "playcount": "4349",
    "@attr": {
      "rank": "1"
    },
    "name": "Palmy"
  },
  {
    "streamable": "0",
    "image": [
      {
        "size": "small",
        "#text": "https://lastfm.freetls.fastly.net/i/u/34s/2a96cbd8b46e442fc41c2b86b821562f.png"
      },
      {
        "size": "medium",
        "#text": "https://lastfm.freetls.fastly.net/i/u/64s/2a96cbd8b46e442fc41c2b86b821562f.png"
      },
      {
        "size": "large",
        "#text": "https://lastfm.freetls.fastly.net/i/u/174s/2a96cbd8b46e442fc41c2b86b821562f.png"
      },
      {
        "size": "extralarge",
        "#text": "https://lastfm.freetls.fastly.net/i/u/300x300/2a96cbd8b46e442fc41c2b86b821562f.png"
      },
      {
        "size": "mega",
        "#text": "https://lastfm.freetls.fastly.net/i/u/300x300/2a96cbd8b46e442fc41c2b86b821562f.png"
      }
    ],
    "mbid": "b9545342-1e6d-4dae-84ac-013374ad8d7c",
    "url": "https://www.last.fm/music/IU",
    "playcount": "3851",
    "@attr": {
      "rank": "2"
    },
    "name": "IU"
  },
  {
    "streamable": "0",
    "image": [
      {
        "size": "small",
        "#text": "https://lastfm.freetls.fastly.net/i/u/34s/2a96cbd8b46e442fc41c2b86b821562f.png"
      },
      {
        "size": "medium",
        "#text": "https://lastfm.freetls.fastly.net/i/u/64s/2a96cbd8b46e442fc41c2b86b821562f.png"
      },
      {
        "size": "large",
        "#text": "https://lastfm.freetls.fastly.net/i/u/174s/2a96cbd8b46e442fc41c2b86b821562f.png"
      },
      {
        "size": "extralarge",
        "#text": "https://lastfm.freetls.fastly.net/i/u/300x300/2a96cbd8b46e442fc41c2b86b821562f.png"
      },
      {
        "size": "mega",
        "#text": "https://lastfm.freetls.fastly.net/i/u/300x300/2a96cbd8b46e442fc41c2b86b821562f.png"
      }
    ],
    "mbid": "",
    "url": "https://www.last.fm/music/LOJ+Worship",
    "playcount": "3093",
    "@attr": {
      "rank": "3"
    },
    "name": "LOJ Worship"
  },
  {
    "streamable": "0",
    "image": [
      {
        "size": "small",
        "#text": "https://lastfm.freetls.fastly.net/i/u/34s/2a96cbd8b46e442fc41c2b86b821562f.png"
      },
      {
        "size": "medium",
        "#text": "https://lastfm.freetls.fastly.net/i/u/64s/2a96cbd8b46e442fc41c2b86b821562f.png"
      },
      {
        "size": "large",
        "#text": "https://lastfm.freetls.fastly.net/i/u/174s/2a96cbd8b46e442fc41c2b86b821562f.png"
      },
      {
        "size": "extralarge",
        "#text": "https://lastfm.freetls.fastly.net/i/u/300x300/2a96cbd8b46e442fc41c2b86b821562f.png"
      },
      {
        "size": "mega",
        "#text": "https://lastfm.freetls.fastly.net/i/u/300x300/2a96cbd8b46e442fc41c2b86b821562f.png"
      }
    ],
    "mbid": "",
    "url": "https://www.last.fm/music/Grezia+Epiphania",
    "playcount": "2021",
    "@attr": {
      "rank": "4"
    },
    "name": "Grezia Epiphania"
  },
  {
    "streamable": "0",
    "image": [
      {
        "size": "small",
        "#text": "https://lastfm.freetls.fastly.net/i/u/34s/2a96cbd8b46e442fc41c2b86b821562f.png"
      },
      {
        "size": "medium",
        "#text": "https://lastfm.freetls.fastly.net/i/u/64s/2a96cbd8b46e442fc41c2b86b821562f.png"
      },
      {
        "size": "large",
        "#text": "https://lastfm.freetls.fastly.net/i/u/174s/2a96cbd8b46e442fc41c2b86b821562f.png"
      },
      {
        "size": "extralarge",
        "#text": "https://lastfm.freetls.fastly.net/i/u/300x300/2a96cbd8b46e442fc41c2b86b821562f.png"
      },
      {
        "size": "mega",
        "#text": "https://lastfm.freetls.fastly.net/i/u/300x300/2a96cbd8b46e442fc41c2b86b821562f.png"
      }
    ],
    "mbid": "",
    "url": "https://www.last.fm/music/Ink+Waruntorn",
    "playcount": "1450",
    "@attr": {
      "rank": "5"
    },
    "name": "Ink Waruntorn"
  },
  {
    "streamable": "0",
    "image": [
      {
        "size": "small",
        "#text": "https://lastfm.freetls.fastly.net/i/u/34s/2a96cbd8b46e442fc41c2b86b821562f.png"
      },
      {
        "size": "medium",
        "#text": "https://lastfm.freetls.fastly.net/i/u/64s/2a96cbd8b46e442fc41c2b86b821562f.png"
      },
      {
        "size": "large",
        "#text": "https://lastfm.freetls.fastly.net/i/u/174s/2a96cbd8b46e442fc41c2b86b821562f.png"
      },
      {
        "size": "extralarge",
        "#text": "https://lastfm.freetls.fastly.net/i/u/300x300/2a96cbd8b46e442fc41c2b86b821562f.png"
      },
      {
        "size": "mega",
        "#text": "https://lastfm.freetls.fastly.net/i/u/300x300/2a96cbd8b46e442fc41c2b86b821562f.png"
      }
    ],
    "mbid": "178131a1-bb63-44dd-8097-a5ac99933c30",
    "url": "https://www.last.fm/music/Home+Free",
    "playcount": "1182",
    "@attr": {
      "rank": "6"
    },
    "name": "Home Free"
  },
  {
    "streamable": "0",
    "image": [
      {
        "size": "small",
        "#text": "https://lastfm.freetls.fastly.net/i/u/34s/2a96cbd8b46e442fc41c2b86b821562f.png"
      },
      {
        "size": "medium",
        "#text": "https://lastfm.freetls.fastly.net/i/u/64s/2a96cbd8b46e442fc41c2b86b821562f.png"
      },
      {
        "size": "large",
        "#text": "https://lastfm.freetls.fastly.net/i/u/174s/2a96cbd8b46e442fc41c2b86b821562f.png"
      },
      {
        "size": "extralarge",
        "#text": "https://lastfm.freetls.fastly.net/i/u/300x300/2a96cbd8b46e442fc41c2b86b821562f.png"
      },
      {
        "size": "mega",
        "#text": "https://lastfm.freetls.fastly.net/i/u/300x300/2a96cbd8b46e442fc41c2b86b821562f.png"
      }
    ],
    "mbid": "",
    "url": "https://www.last.fm/music/symphony+worship",
    "playcount": "934",
    "@attr": {
      "rank": "7"
    },
    "name": "symphony worship"
  },
  {
    "streamable": "0",
    "image": [
      {
        "size": "small",
        "#text": "https://lastfm.freetls.fastly.net/i/u/34s/2a96cbd8b46e442fc41c2b86b821562f.png"
      },
      {
        "size": "medium",
        "#text": "https://lastfm.freetls.fastly.net/i/u/64s/2a96cbd8b46e442fc41c2b86b821562f.png"
      },
      {
        "size": "large",
        "#text": "https://lastfm.freetls.fastly.net/i/u/174s/2a96cbd8b46e442fc41c2b86b821562f.png"
      },
      {
        "size": "extralarge",
        "#text": "https://lastfm.freetls.fastly.net/i/u/300x300/2a96cbd8b46e442fc41c2b86b821562f.png"
      },
      {
        "size": "mega",
        "#text": "https://lastfm.freetls.fastly.net/i/u/300x300/2a96cbd8b46e442fc41c2b86b821562f.png"
      }
    ],
    "mbid": "fc7b8f6d-2777-4a53-957a-1b7c8e7952d2",
    "url": "https://www.last.fm/music/WeLove",
    "playcount": "882",
    "@attr": {
      "rank": "8"
    },
    "name": "WeLove"
  },
  {
    "streamable": "0",
    "image": [
      {
        "size": "small",
        "#text": "https://lastfm.freetls.fastly.net/i/u/34s/2a96cbd8b46e442fc41c2b86b821562f.png"
      },
      {
        "size": "medium",
        "#text": "https://lastfm.freetls.fastly.net/i/u/64s/2a96cbd8b46e442fc41c2b86b821562f.png"
      },
      {
        "size": "large",
        "#text": "https://lastfm.freetls.fastly.net/i/u/174s/2a96cbd8b46e442fc41c2b86b821562f.png"
      },
      {
        "size": "extralarge",
        "#text": "https://lastfm.freetls.fastly.net/i/u/300x300/2a96cbd8b46e442fc41c2b86b821562f.png"
      },
      {
        "size": "mega",
        "#text": "https://lastfm.freetls.fastly.net/i/u/300x300/2a96cbd8b46e442fc41c2b86b821562f.png"
      }
    ],
    "mbid": "dffb8426-b595-4b95-8abe-d07af75e87ef",
    "url": "https://www.last.fm/music/Namika",
    "playcount": "861",
    "@attr": {
      "rank": "9"
    },
    "name": "Namika"
  },
  {
    "streamable": "0",
    "image": [
      {
        "size": "small",
        "#text": "https://lastfm.freetls.fastly.net/i/u/34s/2a96cbd8b46e442fc41c2b86b821562f.png"
      },
      {
        "size": "medium",
        "#text": "https://lastfm.freetls.fastly.net/i/u/64s/2a96cbd8b46e442fc41c2b86b821562f.png"
      },
      {
        "size": "large",
        "#text": "https://lastfm.freetls.fastly.net/i/u/174s/2a96cbd8b46e442fc41c2b86b821562f.png"
      },
      {
        "size": "extralarge",
        "#text": "https://lastfm.freetls.fastly.net/i/u/300x300/2a96cbd8b46e442fc41c2b86b821562f.png"
      },
      {
        "size": "mega",
        "#text": "https://lastfm.freetls.fastly.net/i/u/300x300/2a96cbd8b46e442fc41c2b86b821562f.png"
      }
    ],
    "mbid": "327a36ef-1065-4e76-96d6-b5a89c01a64d",
    "url": "https://www.last.fm/music/Kaylee+Bell",
    "playcount": "823",
    "@attr": {
      "rank": "10"
    },
    "name": "Kaylee Bell"
  },
  {
    "streamable": "0",
    "image": [
      {
        "size": "small",
        "#text": "https://lastfm.freetls.fastly.net/i/u/34s/2a96cbd8b46e442fc41c2b86b821562f.png"
      },
      {
        "size": "medium",
        "#text": "https://lastfm.freetls.fastly.net/i/u/64s/2a96cbd8b46e442fc41c2b86b821562f.png"
      },
      {
        "size": "large",
        "#text": "https://lastfm.freetls.fastly.net/i/u/174s/2a96cbd8b46e442fc41c2b86b821562f.png"
      },
      {
        "size": "extralarge",
        "#text": "https://lastfm.freetls.fastly.net/i/u/300x300/2a96cbd8b46e442fc41c2b86b821562f.png"
      },
      {
        "size": "mega",
        "#text": "https://lastfm.freetls.fastly.net/i/u/300x300/2a96cbd8b46e442fc41c2b86b821562f.png"
      }
    ],
    "mbid": "2c5e2a98-d9ea-46b5-9618-d9bb4863a920",
    "url": "https://www.last.fm/music/George+Ezra",
    "playcount": "775",
    "@attr": {
      "rank": "11"
    },
    "name": "George Ezra"
  },
  {
    "streamable": "0",
    "image": [
      {
        "size": "small",
        "#text": "https://lastfm.freetls.fastly.net/i/u/34s/2a96cbd8b46e442fc41c2b86b821562f.png"
      },
      {
        "size": "medium",
        "#text": "https://lastfm.freetls.fastly.net/i/u/64s/2a96cbd8b46e442fc41c2b86b821562f.png"
      },
      {
        "size": "large",
        "#text": "https://lastfm.freetls.fastly.net/i/u/174s/2a96cbd8b46e442fc41c2b86b821562f.png"
      },
      {
        "size": "extralarge",
        "#text": "https://lastfm.freetls.fastly.net/i/u/300x300/2a96cbd8b46e442fc41c2b86b821562f.png"
      },
      {
        "size": "mega",
        "#text": "https://lastfm.freetls.fastly.net/i/u/300x300/2a96cbd8b46e442fc41c2b86b821562f.png"
      }
    ],
    "mbid": "dabaab7a-e807-435e-b2d7-1403fcdc0671",
    "url": "https://www.last.fm/music/Hillsong+Worship",
    "playcount": "643",
    "@attr": {
      "rank": "12"
    },
    "name": "Hillsong Worship"
  },
  {
    "streamable": "0",
    "image": [
      {
        "size": "small",
        "#text": "https://lastfm.freetls.fastly.net/i/u/34s/2a96cbd8b46e442fc41c2b86b821562f.png"
      },
      {
        "size": "medium",
        "#text": "https://lastfm.freetls.fastly.net/i/u/64s/2a96cbd8b46e442fc41c2b86b821562f.png"
      },
      {
        "size": "large",
        "#text": "https://lastfm.freetls.fastly.net/i/u/174s/2a96cbd8b46e442fc41c2b86b821562f.png"
      },
      {
        "size": "extralarge",
        "#text": "https://lastfm.freetls.fastly.net/i/u/300x300/2a96cbd8b46e442fc41c2b86b821562f.png"
      },
      {
        "size": "mega",
        "#text": "https://lastfm.freetls.fastly.net/i/u/300x300/2a96cbd8b46e442fc41c2b86b821562f.png"
      }
    ],
    "mbid": "",
    "url": "https://www.last.fm/music/H.S.M+Worship",
    "playcount": "630",
    "@attr": {
      "rank": "13"
    },
    "name": "H.S.M Worship"
  },
  {
    "streamable": "0",
    "image": [
      {
        "size": "small",
        "#text": "https://lastfm.freetls.fastly.net/i/u/34s/2a96cbd8b46e442fc41c2b86b821562f.png"
      },
      {
        "size": "medium",
        "#text": "https://lastfm.freetls.fastly.net/i/u/64s/2a96cbd8b46e442fc41c2b86b821562f.png"
      },
      {
        "size": "large",
        "#text": "https://lastfm.freetls.fastly.net/i/u/174s/2a96cbd8b46e442fc41c2b86b821562f.png"
      },
      {
        "size": "extralarge",
        "#text": "https://lastfm.freetls.fastly.net/i/u/300x300/2a96cbd8b46e442fc41c2b86b821562f.png"
      },
      {
        "size": "mega",
        "#text": "https://lastfm.freetls.fastly.net/i/u/300x300/2a96cbd8b46e442fc41c2b86b821562f.png"
      }
    ],
    "mbid": "7292ba91-0465-4679-a697-6891570ae06c",
    "url": "https://www.last.fm/music/Alice+Merton",
    "playcount": "469",
    "@attr": {
      "rank": "14"
    },
    "name": "Alice Merton"
  },
  {
    "streamable": "0",
    "image": [
      {
        "size": "small",
        "#text": "https://lastfm.freetls.fastly.net/i/u/34s/2a96cbd8b46e442fc41c2b86b821562f.png"
      },
      {
        "size": "medium",
        "#text": "https://lastfm.freetls.fastly.net/i/u/64s/2a96cbd8b46e442fc41c2b86b821562f.png"
      },
      {
        "size": "large",
        "#text": "https://lastfm.freetls.fastly.net/i/u/174s/2a96cbd8b46e442fc41c2b86b821562f.png"
      },
      {
        "size": "extralarge",
        "#text": "https://lastfm.freetls.fastly.net/i/u/300x300/2a96cbd8b46e442fc41c2b86b821562f.png"
      },
      {
        "size": "mega",
        "#text": "https://lastfm.freetls.fastly.net/i/u/300x300/2a96cbd8b46e442fc41c2b86b821562f.png"
      }
    ],
    "mbid": "6ef00829-fa94-4fee-a5a6-b28e1208e96a",
    "url": "https://www.last.fm/music/ONE+OK+ROCK",
    "playcount": "444",
    "@attr": {
      "rank": "15"
    },
    "name": "ONE OK ROCK"
  },
  {
    "streamable": "0",
    "image": [
      {
        "size": "small",
        "#text": "https://lastfm.freetls.fastly.net/i/u/34s/2a96cbd8b46e442fc41c2b86b821562f.png"
      },
      {
        "size": "medium",
        "#text": "https://lastfm.freetls.fastly.net/i/u/64s/2a96cbd8b46e442fc41c2b86b821562f.png"
      },
      {
        "size": "large",
        "#text": "https://lastfm.freetls.fastly.net/i/u/174s/2a96cbd8b46e442fc41c2b86b821562f.png"
      },
      {
        "size": "extralarge",
        "#text": "https://lastfm.freetls.fastly.net/i/u/300x300/2a96cbd8b46e442fc41c2b86b821562f.png"
      },
      {
        "size": "mega",
        "#text": "https://lastfm.freetls.fastly.net/i/u/300x300/2a96cbd8b46e442fc41c2b86b821562f.png"
      }
    ],
    "mbid": "e42d8a6b-1857-420e-8d46-c26465e87a59",
    "url": "https://www.last.fm/music/Scary+Pockets",
    "playcount": "440",
    "@attr": {
      "rank": "16"
    },
    "name": "Scary Pockets"
  },
  {
    "streamable": "0",
    "image": [
      {
        "size": "small",
        "#text": "https://lastfm.freetls.fastly.net/i/u/34s/2a96cbd8b46e442fc41c2b86b821562f.png"
      },
      {
        "size": "medium",
        "#text": "https://lastfm.freetls.fastly.net/i/u/64s/2a96cbd8b46e442fc41c2b86b821562f.png"
      },
      {
        "size": "large",
        "#text": "https://lastfm.freetls.fastly.net/i/u/174s/2a96cbd8b46e442fc41c2b86b821562f.png"
      },
      {
        "size": "extralarge",
        "#text": "https://lastfm.freetls.fastly.net/i/u/300x300/2a96cbd8b46e442fc41c2b86b821562f.png"
      },
      {
        "size": "mega",
        "#text": "https://lastfm.freetls.fastly.net/i/u/300x300/2a96cbd8b46e442fc41c2b86b821562f.png"
      }
    ],
    "mbid": "ca7c7521-5ed5-4df7-9302-d357c716f273",
    "url": "https://www.last.fm/music/The+Toys",
    "playcount": "361",
    "@attr": {
      "rank": "17"
    },
    "name": "The Toys"
  },
  {
    "streamable": "0",
    "image": [
      {
        "size": "small",
        "#text": "https://lastfm.freetls.fastly.net/i/u/34s/2a96cbd8b46e442fc41c2b86b821562f.png"
      },
      {
        "size": "medium",
        "#text": "https://lastfm.freetls.fastly.net/i/u/64s/2a96cbd8b46e442fc41c2b86b821562f.png"
      },
      {
        "size": "large",
        "#text": "https://lastfm.freetls.fastly.net/i/u/174s/2a96cbd8b46e442fc41c2b86b821562f.png"
      },
      {
        "size": "extralarge",
        "#text": "https://lastfm.freetls.fastly.net/i/u/300x300/2a96cbd8b46e442fc41c2b86b821562f.png"
      },
      {
        "size": "mega",
        "#text": "https://lastfm.freetls.fastly.net/i/u/300x300/2a96cbd8b46e442fc41c2b86b821562f.png"
      }
    ],
    "mbid": "",
    "url": "https://www.last.fm/music/%E6%89%BF%E6%A1%93",
    "playcount": "336",
    "@attr": {
      "rank": "18"
    },
    "name": "承桓"
  },
  {
    "streamable": "0",
    "image": [
      {
        "size": "small",
        "#text": "https://lastfm.freetls.fastly.net/i/u/34s/2a96cbd8b46e442fc41c2b86b821562f.png"
      },
      {
        "size": "medium",
        "#text": "https://lastfm.freetls.fastly.net/i/u/64s/2a96cbd8b46e442fc41c2b86b821562f.png"
      },
      {
        "size": "large",
        "#text": "https://lastfm.freetls.fastly.net/i/u/174s/2a96cbd8b46e442fc41c2b86b821562f.png"
      },
      {
        "size": "extralarge",
        "#text": "https://lastfm.freetls.fastly.net/i/u/300x300/2a96cbd8b46e442fc41c2b86b821562f.png"
      },
      {
        "size": "mega",
        "#text": "https://lastfm.freetls.fastly.net/i/u/300x300/2a96cbd8b46e442fc41c2b86b821562f.png"
      }
    ],
    "mbid": "20244d07-534f-4eff-b4d4-930878889970",
    "url": "https://www.last.fm/music/Taylor+Swift",
    "playcount": "297",
    "@attr": {
      "rank": "19"
    },
    "name": "Taylor Swift"
  },
  {
    "streamable": "0",
    "image": [
      {
        "size": "small",
        "#text": "https://lastfm.freetls.fastly.net/i/u/34s/2a96cbd8b46e442fc41c2b86b821562f.png"
      },
      {
        "size": "medium",
        "#text": "https://lastfm.freetls.fastly.net/i/u/64s/2a96cbd8b46e442fc41c2b86b821562f.png"
      },
      {
        "size": "large",
        "#text": "https://lastfm.freetls.fastly.net/i/u/174s/2a96cbd8b46e442fc41c2b86b821562f.png"
      },
      {
        "size": "extralarge",
        "#text": "https://lastfm.freetls.fastly.net/i/u/300x300/2a96cbd8b46e442fc41c2b86b821562f.png"
      },
      {
        "size": "mega",
        "#text": "https://lastfm.freetls.fastly.net/i/u/300x300/2a96cbd8b46e442fc41c2b86b821562f.png"
      }
    ],
    "mbid": "85d76093-9865-4605-97fa-8c910929d366",
    "url": "https://www.last.fm/music/Lisa",
    "playcount": "294",
    "@attr": {
      "rank": "20"
    },
    "name": "Lisa"
  }
]